{"cameraMode":{"drawMode":0,"name":"Shaded","section":"Shading Mode"},"sceneLighting":true,"audioPlay":false,"sceneViewState":{"m_AlwaysRefresh":false,"showFog":true,"showSkybox":true,"showFlares":true,"showImageEffects":true,"showParticleSystems":true,"showVisualEffectGraphs":true,"m_FxEnabled":true},"in2DMode":false,"pivot":{"x":10.65449047088623,"y":3.81848406791687,"z":-5.573069095611572},"rotation":{"x":0.025474393740296365,"y":0.7808324098587036,"z":-0.03186951205134392,"w":0.6234595775604248},"size":34.00815200805664,"orthographic":false}